pppipam/__init__.py
pppipam/helpers.py
pppipam/pppipam.py
pppipam-0.1.0.dist-info/LICENSE.txt
pppipam-0.1.0.dist-info/METADATA
pppipam-0.1.0.dist-info/RECORD
pppipam-0.1.0.dist-info/WHEEL
pppipam-0.1.0.dist-info/top_level.txt
