Metadata-Version: 2.1
Name: pppipam
Version: 0.1.0
Summary: Poor person's Python IP Address Manager
Home-page: https://github.com/ayharano/pppipam
Author: Alexandre Harano
Author-email: alexandre@harano.net.br
License: UNKNOWN
Project-URL: Bug Reports, https://github.com/ayharano/pppipam/issues
Project-URL: Source, https://github.com/ayharano/pppipam
Keywords: ip address management ipv4 ipv6 network system administration
Platform: UNKNOWN
Classifier: Development Status :: 3 - Alpha
Classifier: Intended Audience :: Developers
Classifier: Intended Audience :: System Administrators
Classifier: License :: OSI Approved :: MIT License
Classifier: Operating System :: OS Independent
Classifier: Programming Language :: Python :: 3 :: Only
Classifier: Programming Language :: Python :: 3.7
Classifier: Topic :: Software Development :: Libraries
Classifier: Topic :: Software Development :: Libraries :: Python Modules
Classifier: Topic :: System :: Networking
Classifier: Topic :: System :: Systems Administration
Requires-Python: >=3.7, <4
